MANIFEST.in
README.txt
setup.py
rst2marsedit/SendToMarsEdit.applescript
rst2marsedit/__init__.py
rst2marsedit/main.py
rst2marsedit/rst2post.py
rst2marsedit.egg-info/PKG-INFO
rst2marsedit.egg-info/SOURCES.txt
rst2marsedit.egg-info/dependency_links.txt
rst2marsedit.egg-info/entry_points.txt
rst2marsedit.egg-info/not-zip-safe
rst2marsedit.egg-info/requires.txt
rst2marsedit.egg-info/top_level.txt