Metadata-Version: 1.1
Name: rst2marsedit
Version: 1.4.1
Summary: Convert rst input to HTML suitable for use with MarsEdit
Home-page: http://www.doughellmann.com/projects/rst2marsedit/
Author: Doug Hellmann
Author-email: doug.hellmann@gmail.com
License: UNKNOWN
Download-URL: http://www.doughellmann.com/downloads/rst2marsedit-1.4.1.tar.gz
Platform: Any
Classifier: Development Status :: 5 - Production/Stable
Classifier: License :: OSI Approved :: BSD License
Classifier: Programming Language :: Python
Classifier: Intended Audience :: Developers
Classifier: Intended Audience :: End Users/Desktop
Classifier: Environment :: Console
Classifier: Topic :: Documentation
Classifier: Topic :: Text Processing :: Markup :: HTML
Provides: rst2marsedit
